firefly/__init__.py
firefly/application/__init__.py
firefly/application/container.py
firefly/application/service/__init__.py
firefly/application/service/authentication/__init__.py
firefly/application/service/authentication/authenticating_middleware.py
firefly/application/service/core/__init__.py
firefly/application/service/core/auto_generate_aggregate_apis.py
firefly/application/service/core/configure_deployment.py
firefly/application/service/core/configure_storage.py
firefly/application/service/core/execute_batch.py
firefly/application/service/core/load_application_layer.py
firefly/application/service/core/load_containers.py
firefly/application/service/core/load_domain_layer.py
firefly/application/service/core/load_infrastructure_layer.py
firefly/application/service/core/load_presentation_layer.py
firefly/application/service/deployment/__init__.py
firefly/application/service/deployment/deploy.py
firefly/application/service/deployment/migrate_repositories.py
firefly/application/service/iaaa/__init__.py
firefly/application/service/iaaa/authenticating_middleware.py
firefly/application/service/iaaa/authorize_scope.py
firefly/application/service/iaaa/authorizing_middleware.py
firefly/application/service/utilities/__init__.py
firefly/application/service/utilities/generate_api_spec.py
firefly/application/service/utilities/get_dto_schema.py
firefly/application/service/utilities/initialize_project.py
firefly/application/service/utilities/crud/__init__.py
firefly/domain/__init__.py
firefly/domain/error.py
firefly/domain/utils.py
firefly/domain/command/__init__.py
firefly/domain/command/framework_command.py
firefly/domain/command/load_containers.py
firefly/domain/entity/__init__.py
firefly/domain/entity/aggregate_root.py
firefly/domain/entity/entity.py
firefly/domain/entity/json_schema.py
firefly/domain/entity/meta_aggregate.py
firefly/domain/entity/core/__init__.py
firefly/domain/entity/core/api_gateway.py
firefly/domain/entity/core/cli_app.py
firefly_framework-1.2.41.dist-info/LICENSE
firefly_framework-1.2.41.dist-info/METADATA
firefly_framework-1.2.41.dist-info/WHEEL
firefly_framework-1.2.41.dist-info/entry_points.txt
firefly_framework-1.2.41.dist-info/top_level.txt
firefly_framework-1.2.41.dist-info/RECORD
